{
  "ipcMode": null,
  "executionRoleArn": "arn:aws:iam::422133678670:role/ecsTaskExecutionRole",
  "containerDefinitions": [
    {
      "dnsSearchDomains": null,
      "environmentFiles": null,
      "logConfiguration": {
        "logDriver": "awslogs",
        "secretOptions": null,
        "options": {
          "awslogs-group": "/ecs/nftmarketplace-backend",
          "awslogs-region": "ap-southeast-1",
          "awslogs-stream-prefix": "ecs"
        }
      },
      "entryPoint": null,
      "portMappings": [
        {
          "hostPort": 5000,
          "protocol": "tcp",
          "containerPort": 5000
        }
      ],
      "command": null,
      "linuxParameters": null,
      "cpu": 0,
      "environment": [
        {
          "name": "AAA_CLIENT_NOTIFYSECRET",
          "value": "Cf9mx4nAvRuy5vwBY2FCtaKr"
        },
        {
          "name": "AAA_MERCHANT_KEY",
          "value": "mkey-cl1d9k0uc0cw4cmthcuilh31a"
        },
        {
          "name": "AAA_SANDBOX",
          "value": "true"
        },
        {
          "name": "APP_BACKEND_URL",
          "value": "http://ecs.gamepay.sg:8080/nftmarketplace"
        },
        {
          "name": "APP_FRONTEND_URL",
          "value": "http://ecs.gamepay.sg:8080"
        },
        {
          "name": "app-namr",
          "value": "nftmarketplace"
        },
        {
          "name": "CIRCLE_API_URL",
          "value": "https://api-sandbox.circle.com"
        },
        {
          "name": "CIRCLE_TOKEN",
          "value": "QVBJX0tFWTpkNjY4MjcwNGI2NzExMmU0ZGQ0ZDk0ODEwMjgyZDg1OTo4MDc4MWNmZjUwNGFkMjZkZDlkZTBjMTBlNjUwMDNhNA=="
        },
        {
          "name": "CLIENTID_AAA",
          "value": "oacid-cl1d9k0us0cw5cmth3d5608x1"
        },
        {
          "name": "COINBASE_TOKEN",
          "value": "8b1d3f13-3f8e-47fc-892f-40ec5c17b3d7"
        },
        {
          "name": "COINBASE_WEBHOOK_SECRET",
          "value": "f8c5cbc6-e411-4288-af13-e7db9e20f8b9"
        },
        {
          "name": "DOMAIN",
          "value": "http://ecs.gamepay.sg:8080"
        },
        {
          "name": "env",
          "value": "cicd"
        },
        {
          "name": "JWT_SECRET",
          "value": "7dc8b1bd53ac91b1d233a386e27fee0f7c87809e02c3f0a4fa4faf97dfade0f238c82b1b9d34579ce9cc4c86b824d4e6c115"
        },
        {
          "name": "LOG_LEVEL",
          "value": "debug"
        },
        {
          "name": "LOG_S3_ACCESS_KEY",
          "value": "AKIAWESJAYJHI6Y2SAPM"
        },
        {
          "name": "LOG_S3_BUCKET_NAME",
          "value": "gamepay-service-logs-non-prod"
        },
        {
          "name": "LOG_S3_ENABLED",
          "value": "true"
        },
        {
          "name": "LOG_S3_FOLDER_NAME",
          "value": "nft-backend/logs"
        },
        {
          "name": "LOG_S3_SECRET_ACCESS_KEY",
          "value": "h77ARxjMTpjUrXsk/iQap2H15+apcVWZj7vtPEfC"
        },
        {
          "name": "MAIL_PASS",
          "value": "tydjylocaqnpcdzm"
        },
        {
          "name": "MAIL_USER",
          "value": "donotreply@gamepay.sg"
        },
        {
          "name": "MONGO_URL",
          "value": "mongodb+srv://cicd_gamepay:ZZLcZ5HjfnAgE7xa@gamepaycicd.bm7lj.mongodb.net/gamepaycicd?retryWrites=true&w=majority"
        },
        {
          "name": "NODE_ENV",
          "value": "development"
        },
        {
          "name": "PASS_SEC",
          "value": "b76356464f7d58914a9dcc058a46b86c79e72066425f2746fce88cb93dfd1663759b43b1c343b4e57209deaf5f57b3a67664"
        },
        {
          "name": "PINATA_API_KEY",
          "value": "9c9dc9e3d76f7e764013"
        },
        {
          "name": "PINATA_SECRET_KEY",
          "value": "53157df90a66e7a3550acaa2de7097095dc4330922c868197d27dc7e5667667b"
        },
        {
          "name": "PRIVATE_KEY",
          "value": "b76356464f7d58914a9dcc058a46b86c79e72066425f2746fce88cb93dfd1663759b43b1c343b4e57209deaf5f57b3a67664"
        },
        {
          "name": "REWARD_CLAIM_USDT_CONTRACT_ADDRESS",
          "value": "0x555FFe037B3a1812D990781a888Acd412b72e99C"
        },
        {
          "name": "RPC",
          "value": "https://speedy-nodes-nyc.moralis.io/362fc40c1ab324c15e79d4da/bsc/testnet"
        },
        {
          "name": "SECRETID_AAA",
          "value": "f2a74e4c7afc09df29f46f771061f7e61cc7c2ab8249354901057e6dbd3399ef"
        },
        {
          "name": "type",
          "value": "backend"
        }
      ],
      "resourceRequirements": null,
      "ulimits": null,
      "dnsServers": null,
      "mountPoints": [],
      "workingDirectory": null,
      "secrets": null,
      "dockerSecurityOptions": null,
      "memory": null,
      "memoryReservation": 2048,
      "volumesFrom": [],
      "stopTimeout": null,
      "image": "<IMAGE1_NAME>",
      "startTimeout": null,
      "firelensConfiguration": null,
      "dependsOn": null,
      "disableNetworking": null,
      "interactive": null,
      "healthCheck": null,
      "essential": true,
      "links": null,
      "hostname": null,
      "extraHosts": null,
      "pseudoTerminal": null,
      "user": null,
      "readonlyRootFilesystem": null,
      "dockerLabels": null,
      "systemControls": null,
      "privileged": null,
      "name": "nftmarketplace-backend"
    }
  ],
  "placementConstraints": [],
  "memory": "2048",
  "taskRoleArn": "arn:aws:iam::422133678670:role/ecsTaskExecutionRole",
  "compatibilities": [
    "EC2",
    "FARGATE"
  ],
  "taskDefinitionArn": "arn:aws:ecs:ap-southeast-1:422133678670:task-definition/nftmarketplace-backend:6",
  "family": "nftmarketplace-backend",
  "requiresAttributes": [
    {
      "targetId": null,
      "targetType": null,
      "value": null,
      "name": "com.amazonaws.ecs.capability.logging-driver.awslogs"
    },
    {
      "targetId": null,
      "targetType": null,
      "value": null,
      "name": "ecs.capability.execution-role-awslogs"
    },
    {
      "targetId": null,
      "targetType": null,
      "value": null,
      "name": "com.amazonaws.ecs.capability.ecr-auth"
    },
    {
      "targetId": null,
      "targetType": null,
      "value": null,
      "name": "com.amazonaws.ecs.capability.docker-remote-api.1.19"
    },
    {
      "targetId": null,
      "targetType": null,
      "value": null,
      "name": "com.amazonaws.ecs.capability.docker-remote-api.1.21"
    },
    {
      "targetId": null,
      "targetType": null,
      "value": null,
      "name": "com.amazonaws.ecs.capability.task-iam-role"
    },
    {
      "targetId": null,
      "targetType": null,
      "value": null,
      "name": "ecs.capability.execution-role-ecr-pull"
    },
    {
      "targetId": null,
      "targetType": null,
      "value": null,
      "name": "com.amazonaws.ecs.capability.docker-remote-api.1.18"
    },
    {
      "targetId": null,
      "targetType": null,
      "value": null,
      "name": "ecs.capability.task-eni"
    }
  ],
  "pidMode": null,
  "requiresCompatibilities": [
    "FARGATE"
  ],
  "networkMode": "awsvpc",
  "runtimePlatform": {
    "operatingSystemFamily": "LINUX",
    "cpuArchitecture": null
  },
  "cpu": "1024",
  "revision": 6,
  "status": "ACTIVE",
  "inferenceAccelerators": null,
  "proxyConfiguration": null,
  "volumes": []
}